k0emu/__init__.py
k0emu/debug.py
k0emu/processor.py
k0emu/run.py
k0emu/debugger/firmware/Makefile
k0emu/debugger/firmware/debugger.asm
k0emu/tests/__init__.py
k0emu/tests/test_processor.py
k0emu-1.0.0.dist-info/LICENSE.txt
k0emu-1.0.0.dist-info/METADATA
k0emu-1.0.0.dist-info/WHEEL
k0emu-1.0.0.dist-info/entry_points.txt
k0emu-1.0.0.dist-info/top_level.txt
k0emu-1.0.0.dist-info/RECORD
