Metadata-Version: 2.1
Name: k0emu
Version: 1.0.0
Summary: Renesas (NEC) 78K0 emulator
Home-page: https://github.com/mnaberez/k0emu
Author: Mike Naberezny
Author-email: mike@naberezny.com
Maintainer: Mike Naberezny
Maintainer-email: mike@naberezny.com
License: License :: OSI Approved :: BSD License
Platform: UNKNOWN
Classifier: Development Status :: 3 - Alpha
Classifier: Environment :: Console
Classifier: Intended Audience :: Developers
Classifier: Natural Language :: English
Classifier: Operating System :: POSIX
Classifier: Programming Language :: Python
Classifier: Programming Language :: Python :: 3
Classifier: Programming Language :: Python :: 3.4
Classifier: Programming Language :: Python :: 3.5
Classifier: Programming Language :: Python :: 3.6
Classifier: Programming Language :: Python :: 3.7
Classifier: Programming Language :: Python :: 3.8
Classifier: Programming Language :: Assembly
Classifier: Topic :: Software Development :: Debuggers
Classifier: Topic :: Software Development :: Embedded Systems
Classifier: Topic :: Software Development :: Interpreters
Classifier: Topic :: System :: Hardware
Requires-Dist: k0dasm
